Workbook

Sheet Leyenda
A1: Matriz de trazabilidad · Mundo de Fe México
A2: Base: documentos v3 y v3.2 (MVP). Versión 1.0 de la matriz · borrador para VoBo.
A4: Cómo usarla
A5: Hoja Matriz | B5: Una fila por requerimiento. Las columnas A a H salen de los documentos; I y J son un borrador de historia y criterio de aceptación para lo que entra al MVP. Completa K, L y M durante el desarrollo.
A6: Hoja Observaciones | B6: Rastrea cada observación del v3 hacia los requerimientos que la atienden.
A7: Hoja Origen v1 | B7: Rastrea cada necesidad del levantamiento original (v1) hacia los requerimientos actuales; sirve para detectar pérdidas entre versiones.
A8: Hoja Resumen | B8: Avance por fase, hito y estado. Se calcula con fórmulas a partir de la hoja Matriz: no se edita.
A9: Columnas editables
A10: Estado | B10: Elige de la lista: Pendiente, En diseño, En desarrollo, En pruebas, Hecho, Bloqueado. Ejemplo: En pruebas.
A11: Evidencia | B11: Enlace o referencia que demuestra el avance (rama, pantalla del lienzo, resultado de la prueba). Ejemplo: Rama feature/m1-17-acceso · Prueba P-017 aprobada.
A12: Notas | B12: Dudas, decisiones y cambios al requerimiento. Ejemplo: 2026-10-10 · PIN de 6 dígitos confirmado con el Pastor.
A13: Hitos
A14: H1 · 18-oct (núcleo Fase 0) | B14: Objetivo para el 18 de octubre: acceso con WhatsApp + PIN, expediente (EDU) y Contacto, consentimiento, roles base, bitácora, respaldos y despliegue. Es un núcleo, no la Fase 0 completa.
A15: H2 · Fase 0 completa | B15: Avisos y notificaciones, plantillas, diseñador de formularios, permisos por área, seguimiento a visitantes y catálogo de áreas. Estimado: unas 3 semanas después de H1 si se mantiene el ritmo (estimación mía, a recalibrar).
A16: H3 · MVP (Grupos) | B16: Módulo Grupos de Conexión completo, pase de lista sin conexión y dashboards.
A17: Posterior | B17: Fases 2 a 5: Kids, Cursos, Áreas completas, Ministerios, Eventos, vehículos y app nativa.
A18: Origen (colores)
A19: Verde | B19: Recuperado del levantamiento original (v1).
A20: Amarillo | B20: Nuevo o corregido en versiones posteriores (observaciones, respuestas, v3.1 o v3.2).

Sheet Resumen
A1: Resumen de avance
A2: Se calcula con fórmulas a partir de la hoja Matriz. No editar.
A4: Fase | B4: Total | C4: Pendiente | D4: En diseño | E4: En desarrollo | F4: En pruebas | G4: Hecho | H4: Bloqueado | I4: % Hecho
A5: Fase 0 | B5: =COUNTIF(Matriz!$F$2:$F$105,$A5) | C5: =COUNTIFS(Matriz!$F$2:$F$105,$A5,Matriz!$L$2:$L$105,"Pendiente") | D5: =COUNTIFS(Matriz!$F$2:$F$105,$A5,Matriz!$L$2:$L$105,"En diseño") | E5: =COUNTIFS(Matriz!$F$2:$F$105,$A5,Matriz!$L$2:$L$105,"En desarrollo") | F5: =COUNTIFS(Matriz!$F$2:$F$105,$A5,Matriz!$L$2:$L$105,"En pruebas") | G5: =COUNTIFS(Matriz!$F$2:$F$105,$A5,Matriz!$L$2:$L$105,"Hecho") | H5: =COUNTIFS(Matriz!$F$2:$F$105,$A5,Matriz!$L$2:$L$105,"Bloqueado") | I5: =IF(B5=0,0,G5/B5)
A6: Fase 1 | B6: =COUNTIF(Matriz!$F$2:$F$105,$A6) | C6: =COUNTIFS(Matriz!$F$2:$F$105,$A6,Matriz!$L$2:$L$105,"Pendiente") | D6: =COUNTIFS(Matriz!$F$2:$F$105,$A6,Matriz!$L$2:$L$105,"En diseño") | E6: =COUNTIFS(Matriz!$F$2:$F$105,$A6,Matriz!$L$2:$L$105,"En desarrollo") | F6: =COUNTIFS(Matriz!$F$2:$F$105,$A6,Matriz!$L$2:$L$105,"En pruebas") | G6: =COUNTIFS(Matriz!$F$2:$F$105,$A6,Matriz!$L$2:$L$105,"Hecho") | H6: =COUNTIFS(Matriz!$F$2:$F$105,$A6,Matriz!$L$2:$L$105,"Bloqueado") | I6: =IF(B6=0,0,G6/B6)
A7: Fase 2 | B7: =COUNTIF(Matriz!$F$2:$F$105,$A7) | C7: =COUNTIFS(Matriz!$F$2:$F$105,$A7,Matriz!$L$2:$L$105,"Pendiente") | D7: =COUNTIFS(Matriz!$F$2:$F$105,$A7,Matriz!$L$2:$L$105,"En diseño") | E7: =COUNTIFS(Matriz!$F$2:$F$105,$A7,Matriz!$L$2:$L$105,"En desarrollo") | F7: =COUNTIFS(Matriz!$F$2:$F$105,$A7,Matriz!$L$2:$L$105,"En pruebas") | G7: =COUNTIFS(Matriz!$F$2:$F$105,$A7,Matriz!$L$2:$L$105,"Hecho") | H7: =COUNTIFS(Matriz!$F$2:$F$105,$A7,Matriz!$L$2:$L$105,"Bloqueado") | I7: =IF(B7=0,0,G7/B7)
A8: Fase 3 | B8: =COUNTIF(Matriz!$F$2:$F$105,$A8) | C8: =COUNTIFS(Matriz!$F$2:$F$105,$A8,Matriz!$L$2:$L$105,"Pendiente") | D8: =COUNTIFS(Matriz!$F$2:$F$105,$A8,Matriz!$L$2:$L$105,"En diseño") | E8: =COUNTIFS(Matriz!$F$2:$F$105,$A8,Matriz!$L$2:$L$105,"En desarrollo") | F8: =COUNTIFS(Matriz!$F$2:$F$105,$A8,Matriz!$L$2:$L$105,"En pruebas") | G8: =COUNTIFS(Matriz!$F$2:$F$105,$A8,Matriz!$L$2:$L$105,"Hecho") | H8: =COUNTIFS(Matriz!$F$2:$F$105,$A8,Matriz!$L$2:$L$105,"Bloqueado") | I8: =IF(B8=0,0,G8/B8)
A9: Fase 4 | B9: =COUNTIF(Matriz!$F$2:$F$105,$A9) | C9: =COUNTIFS(Matriz!$F$2:$F$105,$A9,Matriz!$L$2:$L$105,"Pendiente") | D9: =COUNTIFS(Matriz!$F$2:$F$105,$A9,Matriz!$L$2:$L$105,"En diseño") | E9: =COUNTIFS(Matriz!$F$2:$F$105,$A9,Matriz!$L$2:$L$105,"En desarrollo") | F9: =COUNTIFS(Matriz!$F$2:$F$105,$A9,Matriz!$L$2:$L$105,"En pruebas") | G9: =COUNTIFS(Matriz!$F$2:$F$105,$A9,Matriz!$L$2:$L$105,"Hecho") | H9: =COUNTIFS(Matriz!$F$2:$F$105,$A9,Matriz!$L$2:$L$105,"Bloqueado") | I9: =IF(B9=0,0,G9/B9)
A10: Fase 5 | B10: =COUNTIF(Matriz!$F$2:$F$105,$A10) | C10: =COUNTIFS(Matriz!$F$2:$F$105,$A10,Matriz!$L$2:$L$105,"Pendiente") | D10: =COUNTIFS(Matriz!$F$2:$F$105,$A10,Matriz!$L$2:$L$105,"En diseño") | E10: =COUNTIFS(Matriz!$F$2:$F$105,$A10,Matriz!$L$2:$L$105,"En desarrollo") | F10: =COUNTIFS(Matriz!$F$2:$F$105,$A10,Matriz!$L$2:$L$105,"En pruebas") | G10: =COUNTIFS(Matriz!$F$2:$F$105,$A10,Matriz!$L$2:$L$105,"Hecho") | H10: =COUNTIFS(Matriz!$F$2:$F$105,$A10,Matriz!$L$2:$L$105,"Bloqueado") | I10: =IF(B10=0,0,G10/B10)
A11: Transversal | B11: =COUNTIF(Matriz!$F$2:$F$105,$A11) | C11: =COUNTIFS(Matriz!$F$2:$F$105,$A11,Matriz!$L$2:$L$105,"Pendiente") | D11: =COUNTIFS(Matriz!$F$2:$F$105,$A11,Matriz!$L$2:$L$105,"En diseño") | E11: =COUNTIFS(Matriz!$F$2:$F$105,$A11,Matriz!$L$2:$L$105,"En desarrollo") | F11: =COUNTIFS(Matriz!$F$2:$F$105,$A11,Matriz!$L$2:$L$105,"En pruebas") | G11: =COUNTIFS(Matriz!$F$2:$F$105,$A11,Matriz!$L$2:$L$105,"Hecho") | H11: =COUNTIFS(Matriz!$F$2:$F$105,$A11,Matriz!$L$2:$L$105,"Bloqueado") | I11: =IF(B11=0,0,G11/B11)
A12: Total | B12: =SUM(B5:B11) | C12: =SUM(C5:C11) | D12: =SUM(D5:D11) | E12: =SUM(E5:E11) | F12: =SUM(F5:F11) | G12: =SUM(G5:G11) | H12: =SUM(H5:H11) | I12: =IF(B12=0,0,G12/B12)
A15: Hito | B15: Total | C15: Pendiente | D15: En diseño | E15: En desarrollo | F15: En pruebas | G15: Hecho | H15: Bloqueado | I15: % Hecho
A16: H1 · 18-oct (núcleo Fase 0) | B16: =COUNTIF(Matriz!$H$2:$H$105,$A16) | C16: =COUNTIFS(Matriz!$H$2:$H$105,$A16,Matriz!$L$2:$L$105,"Pendiente") | D16: =COUNTIFS(Matriz!$H$2:$H$105,$A16,Matriz!$L$2:$L$105,"En diseño") | E16: =COUNTIFS(Matriz!$H$2:$H$105,$A16,Matriz!$L$2:$L$105,"En desarrollo") | F16: =COUNTIFS(Matriz!$H$2:$H$105,$A16,Matriz!$L$2:$L$105,"En pruebas") | G16: =COUNTIFS(Matriz!$H$2:$H$105,$A16,Matriz!$L$2:$L$105,"Hecho") | H16: =COUNTIFS(Matriz!$H$2:$H$105,$A16,Matriz!$L$2:$L$105,"Bloqueado") | I16: =IF(B16=0,0,G16/B16)
A17: H2 · Fase 0 completa | B17: =COUNTIF(Matriz!$H$2:$H$105,$A17) | C17: =COUNTIFS(Matriz!$H$2:$H$105,$A17,Matriz!$L$2:$L$105,"Pendiente") | D17: =COUNTIFS(Matriz!$H$2:$H$105,$A17,Matriz!$L$2:$L$105,"En diseño") | E17: =COUNTIFS(Matriz!$H$2:$H$105,$A17,Matriz!$L$2:$L$105,"En desarrollo") | F17: =COUNTIFS(Matriz!$H$2:$H$105,$A17,Matriz!$L$2:$L$105,"En pruebas") | G17: =COUNTIFS(Matriz!$H$2:$H$105,$A17,Matriz!$L$2:$L$105,"Hecho") | H17: =COUNTIFS(Matriz!$H$2:$H$105,$A17,Matriz!$L$2:$L$105,"Bloqueado") | I17: =IF(B17=0,0,G17/B17)
A18: H3 · MVP (Grupos) | B18: =COUNTIF(Matriz!$H$2:$H$105,$A18) | C18: =COUNTIFS(Matriz!$H$2:$H$105,$A18,Matriz!$L$2:$L$105,"Pendiente") | D18: =COUNTIFS(Matriz!$H$2:$H$105,$A18,Matriz!$L$2:$L$105,"En diseño") | E18: =COUNTIFS(Matriz!$H$2:$H$105,$A18,Matriz!$L$2:$L$105,"En desarrollo") | F18: =COUNTIFS(Matriz!$H$2:$H$105,$A18,Matriz!$L$2:$L$105,"En pruebas") | G18: =COUNTIFS(Matriz!$H$2:$H$105,$A18,Matriz!$L$2:$L$105,"Hecho") | H18: =COUNTIFS(Matriz!$H$2:$H$105,$A18,Matriz!$L$2:$L$105,"Bloqueado") | I18: =IF(B18=0,0,G18/B18)
A19: Posterior | B19: =COUNTIF(Matriz!$H$2:$H$105,$A19) | C19: =COUNTIFS(Matriz!$H$2:$H$105,$A19,Matriz!$L$2:$L$105,"Pendiente") | D19: =COUNTIFS(Matriz!$H$2:$H$105,$A19,Matriz!$L$2:$L$105,"En diseño") | E19: =COUNTIFS(Matriz!$H$2:$H$105,$A19,Matriz!$L$2:$L$105,"En desarrollo") | F19: =COUNTIFS(Matriz!$H$2:$H$105,$A19,Matriz!$L$2:$L$105,"En pruebas") | G19: =COUNTIFS(Matriz!$H$2:$H$105,$A19,Matriz!$L$2:$L$105,"Hecho") | H19: =COUNTIFS(Matriz!$H$2:$H$105,$A19,Matriz!$L$2:$L$105,"Bloqueado") | I19: =IF(B19=0,0,G19/B19)
A20: Total | B20: =SUM(B16:B19) | C20: =SUM(C16:C19) | D20: =SUM(D16:D19) | E20: =SUM(E16:E19) | F20: =SUM(F16:F19) | G20: =SUM(G16:G19) | H20: =SUM(H16:H19) | I20: =IF(B20=0,0,G20/B20)
A23: Sprint | B23: Total | C23: Pendiente | D23: En diseño | E23: En desarrollo | F23: En pruebas | G23: Hecho | H23: Bloqueado | I23: % Hecho
A24: Sprint 0 | B24: =COUNTIF(Matriz!$G$2:$G$105,$A24) | C24: =COUNTIFS(Matriz!$G$2:$G$105,$A24,Matriz!$L$2:$L$105,"Pendiente") | D24: =COUNTIFS(Matriz!$G$2:$G$105,$A24,Matriz!$L$2:$L$105,"En diseño") | E24: =COUNTIFS(Matriz!$G$2:$G$105,$A24,Matriz!$L$2:$L$105,"En desarrollo") | F24: =COUNTIFS(Matriz!$G$2:$G$105,$A24,Matriz!$L$2:$L$105,"En pruebas") | G24: =COUNTIFS(Matriz!$G$2:$G$105,$A24,Matriz!$L$2:$L$105,"Hecho") | H24: =COUNTIFS(Matriz!$G$2:$G$105,$A24,Matriz!$L$2:$L$105,"Bloqueado") | I24: =IF(B24=0,0,G24/B24)
A25: Sprint 1 | B25: =COUNTIF(Matriz!$G$2:$G$105,$A25) | C25: =COUNTIFS(Matriz!$G$2:$G$105,$A25,Matriz!$L$2:$L$105,"Pendiente") | D25: =COUNTIFS(Matriz!$G$2:$G$105,$A25,Matriz!$L$2:$L$105,"En diseño") | E25: =COUNTIFS(Matriz!$G$2:$G$105,$A25,Matriz!$L$2:$L$105,"En desarrollo") | F25: =COUNTIFS(Matriz!$G$2:$G$105,$A25,Matriz!$L$2:$L$105,"En pruebas") | G25: =COUNTIFS(Matriz!$G$2:$G$105,$A25,Matriz!$L$2:$L$105,"Hecho") | H25: =COUNTIFS(Matriz!$G$2:$G$105,$A25,Matriz!$L$2:$L$105,"Bloqueado") | I25: =IF(B25=0,0,G25/B25)
A26: Sprint 2 | B26: =COUNTIF(Matriz!$G$2:$G$105,$A26) | C26: =COUNTIFS(Matriz!$G$2:$G$105,$A26,Matriz!$L$2:$L$105,"Pendiente") | D26: =COUNTIFS(Matriz!$G$2:$G$105,$A26,Matriz!$L$2:$L$105,"En diseño") | E26: =COUNTIFS(Matriz!$G$2:$G$105,$A26,Matriz!$L$2:$L$105,"En desarrollo") | F26: =COUNTIFS(Matriz!$G$2:$G$105,$A26,Matriz!$L$2:$L$105,"En pruebas") | G26: =COUNTIFS(Matriz!$G$2:$G$105,$A26,Matriz!$L$2:$L$105,"Hecho") | H26: =COUNTIFS(Matriz!$G$2:$G$105,$A26,Matriz!$L$2:$L$105,"Bloqueado") | I26: =IF(B26=0,0,G26/B26)
A27: Sprint 3 | B27: =COUNTIF(Matriz!$G$2:$G$105,$A27) | C27: =COUNTIFS(Matriz!$G$2:$G$105,$A27,Matriz!$L$2:$L$105,"Pendiente") | D27: =COUNTIFS(Matriz!$G$2:$G$105,$A27,Matriz!$L$2:$L$105,"En diseño") | E27: =COUNTIFS(Matriz!$G$2:$G$105,$A27,Matriz!$L$2:$L$105,"En desarrollo") | F27: =COUNTIFS(Matriz!$G$2:$G$105,$A27,Matriz!$L$2:$L$105,"En pruebas") | G27: =COUNTIFS(Matriz!$G$2:$G$105,$A27,Matriz!$L$2:$L$105,"Hecho") | H27: =COUNTIFS(Matriz!$G$2:$G$105,$A27,Matriz!$L$2:$L$105,"Bloqueado") | I27: =IF(B27=0,0,G27/B27)
A28: Sprint 4 | B28: =COUNTIF(Matriz!$G$2:$G$105,$A28) | C28: =COUNTIFS(Matriz!$G$2:$G$105,$A28,Matriz!$L$2:$L$105,"Pendiente") | D28: =COUNTIFS(Matriz!$G$2:$G$105,$A28,Matriz!$L$2:$L$105,"En diseño") | E28: =COUNTIFS(Matriz!$G$2:$G$105,$A28,Matriz!$L$2:$L$105,"En desarrollo") | F28: =COUNTIFS(Matriz!$G$2:$G$105,$A28,Matriz!$L$2:$L$105,"En pruebas") | G28: =COUNTIFS(Matriz!$G$2:$G$105,$A28,Matriz!$L$2:$L$105,"Hecho") | H28: =COUNTIFS(Matriz!$G$2:$G$105,$A28,Matriz!$L$2:$L$105,"Bloqueado") | I28: =IF(B28=0,0,G28/B28)
A29: Sprint 5 | B29: =COUNTIF(Matriz!$G$2:$G$105,$A29) | C29: =COUNTIFS(Matriz!$G$2:$G$105,$A29,Matriz!$L$2:$L$105,"Pendiente") | D29: =COUNTIFS(Matriz!$G$2:$G$105,$A29,Matriz!$L$2:$L$105,"En diseño") | E29: =COUNTIFS(Matriz!$G$2:$G$105,$A29,Matriz!$L$2:$L$105,"En desarrollo") | F29: =COUNTIFS(Matriz!$G$2:$G$105,$A29,Matriz!$L$2:$L$105,"En pruebas") | G29: =COUNTIFS(Matriz!$G$2:$G$105,$A29,Matriz!$L$2:$L$105,"Hecho") | H29: =COUNTIFS(Matriz!$G$2:$G$105,$A29,Matriz!$L$2:$L$105,"Bloqueado") | I29: =IF(B29=0,0,G29/B29)
A30: — | B30: =COUNTIF(Matriz!$G$2:$G$105,$A30) | C30: =COUNTIFS(Matriz!$G$2:$G$105,$A30,Matriz!$L$2:$L$105,"Pendiente") | D30: =COUNTIFS(Matriz!$G$2:$G$105,$A30,Matriz!$L$2:$L$105,"En diseño") | E30: =COUNTIFS(Matriz!$G$2:$G$105,$A30,Matriz!$L$2:$L$105,"En desarrollo") | F30: =COUNTIFS(Matriz!$G$2:$G$105,$A30,Matriz!$L$2:$L$105,"En pruebas") | G30: =COUNTIFS(Matriz!$G$2:$G$105,$A30,Matriz!$L$2:$L$105,"Hecho") | H30: =COUNTIFS(Matriz!$G$2:$G$105,$A30,Matriz!$L$2:$L$105,"Bloqueado") | I30: =IF(B30=0,0,G30/B30)
A31: Total | B31: =SUM(B24:B30) | C31: =SUM(C24:C30) | D31: =SUM(D24:D30) | E31: =SUM(E24:E30) | F31: =SUM(F24:F30) | G31: =SUM(G24:G30) | H31: =SUM(H24:H30) | I31: =IF(B31=0,0,G31/B31)
A34: Validación de requerimientos
A35: VoBo pendiente | B35: =COUNTIF(Matriz!$K$2:$K$105,A35)
A36: Aprobado | B36: =COUNTIF(Matriz!$K$2:$K$105,A36)
A37: Por definir | B37: =COUNTIF(Matriz!$K$2:$K$105,A37)
A38: Rechazado | B38: =COUNTIF(Matriz!$K$2:$K$105,A38)

Sheet Matriz
A1: ID | B1: Módulo | C1: Requerimiento | D1: Origen | E1: Alcance | F1: Fase | G1: Sprint | H1: Hito | I1: Historia de usuario (borrador) | J1: Criterio de aceptación / prueba (borrador) | K1: Validación | L1: Estado | M1: Evidencia | N1: Notas
A2: CFG-01 | B2: Configuración (low-code) | C2: Diseñador de formularios: crear, editar y deshabilitar campos en peticiones de oración y en los datos del expediente. Versión básica con tipos de campo comunes. | D2: v3 + Obs. 2 | E2: MVP | F2: Fase 0 | G2: Sprint 2 | H2: H2 · Fase 0 completa | I2: Como administrador quiero crear y editar formularios sin programar para adaptar peticiones y datos del expediente. | J2: Crear un formulario con los tipos de campo básicos, guardarlo, deshabilitar un campo y comprobar que las respuestas previas se conservan. | K2: VoBo pendiente | L2: Pendiente
A3: CFG-02 | B3: Configuración (low-code) | C3: Layouts y pantallas customizables: vistas, secciones visibles y tableros según rol o departamento. | D3: v2 | E3: Fuera del MVP | F3: Fase 5 | G3: — | H3: Posterior | I3: Se define al iniciar la fase. | J3: Se define al iniciar la fase. | K3: VoBo pendiente | L3: Pendiente
A4: CFG-03 | B4: Configuración (low-code) | C4: Gestor de flujos y permisos: creación de roles, niveles de acceso y reglas de negocio desde un panel visual. | D4: v2 | E4: Fuera del MVP | F4: Fase 5 | G4: — | H4: Posterior | I4: Se define al iniciar la fase. | J4: Se define al iniciar la fase. | K4: VoBo pendiente | L4: Pendiente
A5: CFG-04 | B5: Configuración (low-code) | C5: Plantillas de notificación editables (avisos, recordatorios de reunión, activación de cuenta). | D5: v3 | E5: MVP básico | F5: Fase 0 | G5: Sprint 2 | H5: H2 · Fase 0 completa | I5: Como administrador quiero editar los mensajes automáticos para ajustar el tono sin depender de TI. | J5: Editar una plantilla y verificar que el siguiente aviso usa el texto nuevo. | K5: VoBo pendiente | L5: Pendiente
A6: CFG-05 | B6: Configuración (low-code) | C6: Configurabilidad incremental: formularios primero; layouts y flujos avanzados después. | D6: v3 | E6: MVP | F6: Fase 0 | G6: Sprint 2 | H6: H2 · Fase 0 completa | I6: Como equipo queremos entregar la configurabilidad por fases para reducir riesgo. | J6: El diseñador de formularios está disponible en el MVP; layouts y flujos avanzados quedan en el backlog de Fase 5. | K6: VoBo pendiente | L6: Pendiente
A7: CFG-06 | B7: Configuración (low-code) | C7: Modelo híbrido de formularios: tablas fijas para las entidades principales (Persona/EDU, Grupo, Reunión, Ofrenda) con campos personalizados añadidos por el diseñador, y formularios independientes cuyas respuestas se guardan de forma flexible. | D7: Obs. 2 | E7: MVP | F7: Fase 0 | G7: Sprint 2 | H7: H2 · Fase 0 completa | I7: Como administrador quiero agregar campos personalizados a Persona, Grupo y Reunión para registrar lo que la iglesia necesita. | J7: Agregar un campo (ej. talla) a Persona; aparece en el formulario y se guarda sin alterar la estructura de la base. | K7: VoBo pendiente | L7: Pendiente
A8: CFG-07 | B8: Configuración (low-code) | C8: Campos de tipo «relación» (Persona/EDU, Grupo, Área) que conservan el vínculo por ID, para que reportes y estadísticas crucen formularios. | D8: Obs. 2 | E8: MVP | F8: Fase 0 | G8: Sprint 2 | H8: H2 · Fase 0 completa | I8: Como administrador quiero campos que apunten a una Persona o Grupo para cruzar datos en reportes. | J8: Un campo de relación guarda el ID de la Persona y el reporte lo cruza con su grupo. | K8: VoBo pendiente | L8: Pendiente
A9: CFG-08 | B9: Configuración (low-code) | C9: Un campo nunca se borra, solo se deshabilita. Cada cambio del formulario genera versión. Los campos «reportables» se marcan para consultas y estadísticas. | D9: Obs. 2 | E9: MVP | F9: Fase 0 | G9: Sprint 2 | H9: H2 · Fase 0 completa | I9: Como administrador quiero versionar los formularios para no perder respuestas antiguas. | J9: Deshabilitar un campo no borra respuestas; cada cambio crea versión; un campo reportable aparece en reportes. | K9: VoBo pendiente | L9: Pendiente
A10: M1-01 | B10: M1 Identidad y comunicación | C10: Expediente Digital Único (EDU) con los campos de la «Radiografía de miembros GC»: foto; nombre, apellidos, fecha de nacimiento (la edad se calcula); calle y número, colonia, código postal, alcaldía; teléfono fijo y celular; correo; grupo de conexión, líder y sector (texto provisional hasta el módulo de Grupos); tiempo en Mundo de Fe; ministerios en que sirve; devocional personal; Oración de Familias en Acción; otros cursos y observaciones. La foto se guarda en una carpeta del servidor con su ruta en la base de datos y solo se ve con sesión y permisos. | D10: v3 + Radiografía | E10: MVP | F10: Fase 0 | G10: Sprint 1 | H10: H1 · 18-oct (núcleo Fase 0) | I10: Como pastor quiero un expediente por persona con los datos de la Radiografía de miembros GC para conocer a mi gente. | J10: Crear un EDU con foto y los campos de la Radiografía, buscarlo sin importar acentos y consultarlo con el rol adecuado; la foto solo se ve con sesión. | K10: VoBo pendiente | L10: En pruebas | M10: Rama feature/m1-01-expediente · 56 pruebas de backend y 6 de frontend pasan | N10: 2026-10-05 · Falta revisar con la iglesia que los campos y el orden de la Radiografía estén completos.
A11: M1-02 | B11: M1 Identidad y comunicación | C11: Los datos que se recaban en el EDU son configurables. | D11: v3 | E11: MVP | F11: Fase 0 | G11: Sprint 2 | H11: H2 · Fase 0 completa | I11: Como administrador quiero definir qué datos se recaban en el expediente. | J11: Agregar un campo configurable al EDU y verlo en el alta (depende de CFG-06). | K11: VoBo pendiente | L11: Pendiente
A12: M1-03 | B12: M1 Identidad y comunicación | C12: Vínculo familiar y tutor–menor en el expediente, y lista de personas autorizadas a recoger a cada menor (insumo del módulo Kids). | D12: Nuevo v3 | E12: Fuera del MVP | F12: Fase 2 | G12: — | H12: Posterior | I12: Se define al iniciar la fase. | J12: Se define al iniciar la fase. | K12: VoBo pendiente | L12: Pendiente
A13: M1-04 | B13: M1 Identidad y comunicación | C13: Registro de bienes: vehículos y motos (placas, marca, modelo, color) u otros bienes personales traídos a la iglesia, asociados al expediente. | D13: v2 | E13: Fuera del MVP | F13: Fase 5 | G13: — | H13: Posterior | I13: Se define al iniciar la fase. | J13: Se define al iniciar la fase. | K13: VoBo pendiente | L13: Pendiente
A14: M1-05 | B14: M1 Identidad y comunicación | C14: Alertas rápidas: el personal de seguridad o ushers busca una placa y envía una notificación push prioritaria al propietario (auto mal estacionado, acceso bloqueado, etc.). | D14: v2 | E14: Fuera del MVP | F14: Fase 5 | G14: — | H14: Posterior | I14: Se define al iniciar la fase. | J14: Se define al iniciar la fase. | K14: VoBo pendiente | L14: Pendiente
A15: M1-06 | B15: M1 Identidad y comunicación | C15: Canal de respaldo para alertas cuando el propietario no tiene la app instalada o no concedió permisos de notificación (p. ej. WhatsApp o SMS). Por definir canal. | D15: Nuevo v3 | E15: Fuera del MVP | F15: Fase 5 | G15: — | H15: Posterior | I15: Se define al iniciar la fase. | J15: Se define al iniciar la fase. | K15: Por definir | L15: Pendiente
A16: M1-07 | B16: M1 Identidad y comunicación | C16: RBAC configurable con la jerarquía: Administrador Técnico, Pastor General, Ancianos (como Pastor, con limitantes en finanzas), Directores/Supervisores, Líderes/Maestros, Servidores, Miembro/Asistente. | D16: v3 + Resp. P8 | E16: MVP | F16: Fase 0 | G16: Sprint 1 | H16: H1 · 18-oct (núcleo Fase 0) | I16: Como administrador quiero asignar roles con la jerarquía acordada para controlar accesos. | J16: Un Líder no accede a otro grupo; los Ancianos no ven finanzas; el Pastor ve todo. | K16: VoBo pendiente | L16: En pruebas | M16: Rama feature/paso-6-roles-permisos · pruebas de backend y 97 de frontend pasan; lint, estilos y compilación limpios | N16: 2026-10-29 · Roles base más la Secretaria; asignación con jerarquía (nadie otorga un rol más alto que el suyo, solo el Super Usuario asigna Super Usuario); baja y traslado solo por un superior.
A17: M1-08 | B17: M1 Identidad y comunicación | C17: Permisos por área y por grupo. Requiere un catálogo mínimo de áreas (ver M5-01). | D17: v3 | E17: MVP | F17: Fase 0 | G17: Sprint 1 | H17: H2 · Fase 0 completa | I17: Como director quiero permisos por área o grupo para acotar lo que ve cada servidor. | J17: Un permiso por grupo permite ver solo ese grupo. | K17: VoBo pendiente | L17: En pruebas | M17: Rama feature/m3-grupos · 88 pruebas de backend y 7 de frontend pasan | N17: 2026-10-24 · Alcance por grupo implementado en el módulo Grupos.
A18: M1-09 | B18: M1 Identidad y comunicación | C18: Avisos globales y notificaciones push segmentables por audiencia. | D18: v3 | E18: MVP | F18: Fase 0 | G18: Sprint 2 | H18: H2 · Fase 0 completa | I18: Como pastor quiero enviar avisos segmentados para llegar a la audiencia correcta. | J18: Enviar un aviso a un grupo y verificar que solo sus integrantes lo reciben. | K18: VoBo pendiente | L18: En pruebas | M18: Rama feature/m1-09-notificaciones · pruebas de backend y 66 de frontend pasan; claves VAPID de QA configuradas | N18: 2026-10-26 · Notificaciones push con sonido y vibración para mensajes del tablero y estudio nuevo, solo a quien puede leerlos; se activan por dispositivo y se pueden apagar en Configuración. Pendiente: probar en Samsung S23 e iPhone reales y los avisos de la iglesia en general (no ligados a un grupo).
A19: M1-10 | B19: M1 Identidad y comunicación | C19: Los avisos no son públicos. El visitante recibe por WhatsApp un enlace a un espacio con rol «Visitante» donde consulta avisos y eventos. | D19: v3 + Resp. P8 | E19: MVP | F19: Fase 0 | G19: Sprint 2 | H19: H2 · Fase 0 completa | I19: Como visitante quiero consultar avisos y eventos desde un enlace sin ser miembro. | J19: Un Contacto abre el enlace de WhatsApp y ve avisos con rol Visitante, sin acceso a otros datos. | K19: VoBo pendiente | L19: En pruebas | M19: Rama feature/paso-5-invitaciones · pruebas de backend y 93 de frontend pasan; lint, estilos y compilación limpios | N19: 2026-10-27 · Rol por defecto Miembro / Asistente al invitar; invitación por enlace o QR con aprobación del líder (sala de espera) y asignación manual desde la ficha de la persona, con notificaciones.
A20: M1-11 | B20: M1 Identidad y comunicación | C20: Aviso de privacidad y consentimiento al registrar a cualquier persona o activar una cuenta, con consentimiento aparte para la foto. Cada consentimiento guarda la versión del aviso y la fecha. Por ahora el texto es genérico de ejemplo y debe sustituirse por el oficial antes de producción. | D20: v3 | E20: MVP | F20: Fase 0 | G20: Sprint 1 | H20: H1 · 18-oct (núcleo Fase 0) | I20: Como persona registrada quiero conocer y aceptar el aviso de privacidad. | J20: No se guarda un registro sin consentimiento; queda versión del aviso, fecha y alcance (foto, menores). | K20: VoBo pendiente | L20: En pruebas | M20: Rama feature/m1-01-expediente · 56 pruebas de backend y 6 de frontend pasan | N20: 2026-10-05 · Texto del aviso genérico; sustituir por el oficial antes de producción.
A21: M1-12 | B21: M1 Identidad y comunicación | C21: Tres niveles de registro: Contacto (nombre, WhatsApp, procedencia, consentimiento), Participante y EDU completo. Un Contacto puede ascender a EDU sin duplicarse; el número de WhatsApp sirve para detectar duplicados. | D21: Obs. 3 y 10 | E21: MVP | F21: Fase 0 | G21: Sprint 1 | H21: H1 · 18-oct (núcleo Fase 0) | I21: Como encargado de bienvenida quiero registrar a un visitante con nombre y WhatsApp para darle seguimiento. | J21: Registrar un Contacto; al ascender a EDU no se duplica; el mismo WhatsApp detecta duplicado. | K21: VoBo pendiente | L21: En pruebas | M21: Rama feature/personas-paso-4 · pruebas de backend y 85 de frontend pasan; lint, estilos y compilación limpios | N21: 2026-10-27 · Niveles contacto → participante → expediente completo, ahora explicados en la ficha; duplicados por WhatsApp.
A22: M1-13 | B22: M1 Identidad y comunicación | C22: Atributo de procedencia: miembro de la iglesia local, invitado de grupo (no asiste a la iglesia), visitante de la iglesia o externo. | D22: Obs. 3 | E22: MVP | F22: Fase 0 | G22: Sprint 1 | H22: H1 · 18-oct (núcleo Fase 0) | I22: Como pastor quiero saber la procedencia de cada persona. | J22: Valores: miembro, invitado de grupo, visitante y externo; se puede filtrar en listas. | K22: VoBo pendiente | L22: En pruebas | M22: Rama feature/m1-01-expediente · 56 pruebas de backend y 6 de frontend pasan | N22: 2026-10-05 · Procedencia en el alta y en la ficha.
A23: M1-14 | B23: M1 Identidad y comunicación | C23: Bitácora de movimientos del EDU: altas, bajas, cambios de grupo o área, con fecha y motivo. Al dejar la iglesia solo se conservan fecha y motivo. | D23: Resp. P8 | E23: MVP | F23: Fase 0 | G23: Sprint 1 | H23: H1 · 18-oct (núcleo Fase 0) | I23: Como pastor quiero un historial de altas, bajas y cambios con fecha y motivo. | J23: Una baja conserva solo fecha y motivo; el movimiento aparece en el historial del EDU. | K23: VoBo pendiente | L23: En pruebas | M23: Rama feature/personas-paso-4 · pruebas de backend y 85 de frontend pasan; lint, estilos y compilación limpios | N23: 2026-10-27 · Historial de movimientos con fecha y motivo; ahora incluye traslado a otra iglesia con su destino, y la baja retira a la persona de sus grupos.
A24: M1-16 | B24: M1 Identidad y comunicación | C24: Control de modificaciones: solo roles definidos pueden modificar datos sensibles (ofrendas, asistencias). Toda consulta o modificación queda en bitácora. | D24: Obs. 5 | E24: MVP | F24: Fase 0 | G24: Sprint 1 | H24: H1 · 18-oct (núcleo Fase 0) | I24: Como pastor quiero que solo ciertos roles modifiquen datos sensibles. | J24: Modificar una asistencia o una ofrenda exige rol autorizado y motivo, y queda en bitácora. | K24: VoBo pendiente | L24: En pruebas | M24: Rama feature/navegacion-dashboard-paso-2 · pruebas de backend y 77 de frontend pasan; lint, estilos y compilación limpios | N24: 2026-10-27 · Bitácora con niveles tipo semáforo, filtros, paginación y gráfica de errores por día. Consultar el resumen también exige el permiso de bitácora.
A25: M1-17 | B25: M1 Identidad y comunicación | C25: Acceso con número de WhatsApp o correo y PIN de 6 dígitos (contraseña de 10+ caracteres para roles sensibles como Pastor, Tesorero y Administrador). La cuenta se activa con un enlace de un solo uso que caduca, enviado desde el WhatsApp de quien invita (sin costo). Recuperación: reinicio por Líder o administrador y enlace por correo si lo tiene. Sin SMS en el MVP. | D25: Nuevo v3.1 / v3.3 | E25: MVP | F25: Fase 0 | G25: Sprint 0 | H25: H1 · 18-oct (núcleo Fase 0) | I25: Como usuario quiero entrar con mi WhatsApp o correo y un PIN sencillo. | J25: Activar la cuenta con enlace de un solo uso, entrar con PIN de 6 dígitos (contraseña fuerte en roles sensibles), bloqueo tras 5 intentos y recuperación por Líder, administrador o correo. | K25: VoBo pendiente | L25: Hecho | M25: Rama feature/m1-17-acceso · 33 pruebas de backend y 4 de frontend pasan · Flujo invitar, activar y entrar probado por Edgar en navegador de escritorio | N25: 2026-10-05 · Pendiente repetir la prueba en Android/iOS (se cubre con NF-07).
A26: M1-18 | B26: M1 Identidad y comunicación | C26: Contacto de seguimiento a visitantes: un responsable asignado y estado (nuevo, contactado, invitado a consolidación, se integró, no continuó). | D26: Obs. 10 | E26: MVP mínimo | F26: Fase 0 | G26: Sprint 2 | H26: H2 · Fase 0 completa | I26: Como responsable de seguimiento quiero ver a quién contactar y en qué estado va. | J26: Un Contacto tiene responsable y estado; cada cambio de estado queda registrado. | K26: VoBo pendiente | L26: Pendiente
A27: M1-19 | B27: M1 Identidad y comunicación | C27: Dashboard y tablero de mensajes por módulo como componentes genéricos: el tablero (y las peticiones) se registran por origen y cada módulo decide quién publica y quién lee; los gráficos del dashboard viven en el sistema de diseño. Grupos de Conexión es el primer módulo en usarlos. | D27: Obs. 7 | E27: MVP | F27: Fase 0 | G27: Sprint 5 | H27: H3 · MVP (Grupos) | I27: Como líder o supervisor quiero un dashboard y un tablero de mensajes en mi módulo. | J27: El módulo Grupos muestra dashboard y tablero con permisos por rol. | K27: VoBo pendiente | L27: En pruebas | M27: Rama feature/navegacion-dashboard-paso-2 · pruebas de backend y 77 de frontend pasan; lint, estilos y compilación limpios | N27: 2026-10-27 · Tablero y gráficas como componentes genéricos; grupos es el primer origen. Barra superior con Cerrar sesión, menú por categorías, Inicio como dashboard con accesos rápidos y resumen de grupos, y color de la aplicación elegible (v3.15).
A28: M1-21 | B28: M1 Identidad y comunicación | C28: Cambio de número: el usuario lo actualiza con su PIN actual, el Líder recibe un aviso y queda en bitácora. Si perdió número y teléfono, el Líder o administrador reinicia su acceso. La identidad estable es un ID interno, no el número. El aviso al Líder se activa cuando exista el módulo de Grupos. | D28: Nuevo v3.3 | E28: MVP | F28: Fase 0 | G28: Sprint 1 | H28: H1 · 18-oct (núcleo Fase 0) | I28: Como persona que cambió de número quiero actualizarlo sin perder mi historial. | J28: Cambio con el PIN actual, aviso al Líder y registro en bitácora; si perdió número y teléfono, el Líder o administrador reinicia el acceso. | K28: VoBo pendiente | L28: En pruebas | M28: Rama feature/m1-17-acceso · 33 pruebas de backend y 4 de frontend pasan | N28: 2026-10-05 · El aviso al Líder se activa cuando exista Grupos (Sprint 3).
A29: M1-22 | B29: M1 Identidad y comunicación | C29: Bloqueo de cuenta tras 5 intentos fallidos durante 15 minutos (configurable), limitación de intentos por IP y sesión de 90 días renovable con el uso. | D29: Nuevo v3.3 | E29: MVP | F29: Fase 0 | G29: Sprint 0 | H29: H1 · 18-oct (núcleo Fase 0) | I29: Como iglesia queremos proteger las cuentas de intentos de adivinar el PIN. | J29: Tras 5 intentos fallidos la cuenta se bloquea 15 minutos; sesión de 90 días renovable. | K29: VoBo pendiente | L29: En pruebas | M29: Rama feature/m1-17-acceso · 33 pruebas de backend y 4 de frontend pasan | N29: 2026-10-05 · Límite de intentos por IP: 30 por minuto.
A30: M1-23 | B30: M1 Identidad y comunicación | C30: Procesos de desarrollo discipular: catálogo configurable (14 procesos de la Radiografía: Nacimiento Espiritual, Consolidación, Peniel, Bautismo en el Espíritu Santo, Bautismo en Agua, Sanidad Total, Fundamentos de la Vida Cristiana, Fundamentos Doctrinales, Fundamentos de Liderazgo, Avanzado hacia la Meta, Visión G. de Conexión, Espíritu Santo, Panorama Bíblico y Lanzamiento) y avance por persona con fecha y nombre del maestro. | D30: Nuevo v3.4 | E30: MVP | F30: Fase 0 | G30: Sprint 1 | H30: H1 · 18-oct (núcleo Fase 0) | I30: Como líder quiero registrar los procesos de discipulado que ha cursado cada persona, con fecha y maestro. | J30: Marcar procesos del catálogo con fecha y maestro, guardarlos y verlos en la ficha; el catálogo es configurable. | K30: VoBo pendiente | L30: En pruebas | M30: Rama feature/m1-01-expediente · 56 pruebas de backend y 6 de frontend pasan | N30: 2026-10-05 · 14 procesos sembrados desde la Radiografía.
A31: M1-24 | B31: M1 Identidad y comunicación | C31: Administrador de roles y permisos: se crean roles y, por módulo, pantalla y acción, se elige lo que cada uno puede hacer. El Super Usuario, el Pastor y la Secretaria lo administran; nadie está por encima del Super Usuario y solo él asigna ese rol. Nadie concede un permiso que no tiene ni crea o cambia un rol de su nivel o superior. Un rol en uso no se desactiva y todo cambio queda en bitácora. | D31: Respuesta v3.19 | E31: MVP | F31: Fase 0 | G31: Sprint 5 | H31: H2 · Fase 0 completa | I31: Como administrador quiero crear roles y elegir, por módulo, pantalla y acción, lo que puede hacer cada uno, para que los permisos no se hagan bolas. | J31: Crear un rol con permisos, no poder conceder los que no se tienen ni editar un rol de nivel igual o superior, y ver en la bitácora quién cambió qué. | K31: VoBo pendiente | L31: En pruebas | M31: Rama feature/paso-6-roles-permisos · pruebas de backend y 97 de frontend pasan; lint, estilos y compilación limpios | N31: 2026-10-29 · Catálogo de permisos, pantalla de roles con matriz, duplicado y desactivación, rol Secretaria y vista de lo que puede hacer cada persona. Falta: roles de unidad con alcance (siguiente entrega).
A32: M1-25 | B32: M1 Identidad y comunicación | C32: Ministerios: áreas de servicio de la iglesia (cafetería, librería, niños, danza, etc.), cada uno con encargado, respaldo y servidores. Quien participa en un ministerio ve solo ese ministerio, y su rol vale únicamente dentro de él, independiente de sus roles en grupos u otros ministerios. Cada ministerio tiene su propio tablero de avisos y sus peticiones de oración. | D32: Respuesta v3.21 | E32: MVP | F32: Fase 0 | G32: Sprint 5 | H32: H2 · Fase 0 completa | I32: Como encargado de un ministerio quiero administrar a mi gente y mis avisos sin ver lo de otros ministerios ni grupos. | J32: Un encargado de la cafetería no ve la librería; el mismo encargado como asistente de un grupo no gestiona ese grupo; un servidor no agrega integrantes. | K32: VoBo pendiente | L32: En pruebas | M32: Rama feature/paso-8-ministerios-mi-cuenta · pruebas de backend y 108 de frontend pasan; lint, estilos y compilación limpios | N32: 2026-10-30 · Ministerios (antes unidades) con encargado, respaldo y servidores, alcance propio, tablero de avisos y peticiones de oración.
A33: M1-26 | B33: M1 Identidad y comunicación | C33: Roles de grupos y de ministerios configurables: encargado (líder en un grupo), respaldo y servidores, además de los roles que ya existían. Quien administra roles (Super Usuario, Pastor y Secretaria) crea roles y elige, por acción, lo que puede hacer quien los tiene dentro de un grupo o de un ministerio. | D33: Respuesta v3.21 | E33: MVP | F33: Fase 0 | G33: Sprint 5 | H33: H2 · Fase 0 completa | I33: Como administrador quiero definir qué puede hacer el encargado, el respaldo y los servidores de cada grupo y ministerio, para no depender de reglas fijas. | J33: Crear un rol de ministerio con permisos; quitarle un permiso al encargado cambia lo que puede hacer; un rol que administra gente solo lo asigna la administración; un rol base no se desactiva. | K33: VoBo pendiente | L33: En pruebas | M33: Rama feature/paso-8-ministerios-mi-cuenta · pruebas de backend y 108 de frontend pasan; lint, estilos y compilación limpios | N33: 2026-10-30 · Roles de ministerio y de grupo configurables desde Roles y permisos; roles base y roles nuevos; las ofrendas y peticiones de grupo siguen con reglas fijas.
A34: M1-27 | B34: M1 Identidad y comunicación | C34: Mi cuenta: la persona corrige sus datos básicos (nombre, fecha de nacimiento, domicilio, teléfono fijo, devocional, oración de familias y foto). No edita nada que afecte su acceso (WhatsApp, correo, PIN) ni sus relaciones con la iglesia (grupo, sector, ministerios, roles, nivel). | D34: Respuesta v3.21 | E34: MVP | F34: Fase 0 | G34: Sprint 5 | H34: H2 · Fase 0 completa | I34: Como persona quiero corregir mis datos básicos desde Mi cuenta sin poder cambiar mi acceso ni mi grupo. | J34: Corregir nombre y domicilio; intentar cambiar WhatsApp, correo, nivel o grupo no tiene efecto; la foto pide aceptar su uso; la bitácora no guarda los valores. | K34: VoBo pendiente | L34: En pruebas | M34: Rama feature/paso-8-ministerios-mi-cuenta · pruebas de backend y 108 de frontend pasan; lint, estilos y compilación limpios | N34: 2026-10-30 · Mi cuenta editable: datos básicos y foto con consentimiento; sin acceso ni relaciones.
A35: M1-28 | B35: M1 Identidad y comunicación | C35: Peticiones de oración personales: toda persona con sesión puede pedir oración y ve la sección de oración. Ve las suyas; las ve también la dirección que consulta todas las peticiones, y el equipo de oración si las comparte con él. | D35: Respuesta v3.22 | E35: MVP | F35: Fase 0 | G35: Sprint 5 | H35: H2 · Fase 0 completa | I35: Como persona quiero pedir oración desde la aplicación y ver mis peticiones. | J35: Cualquier cuenta registra una petición personal y la ve; otra cuenta no; el equipo de oración solo lee las compartidas con él. | K35: VoBo pendiente | L35: En pruebas | M35: Rama feature/paso-9-oraciones-vehiculos · pruebas de backend y 110 de frontend pasan; lint, estilos y compilación limpios | N35: 2026-10-30 · Origen de peticiones personales para toda cuenta.
A36: M1-29 | B36: M1 Identidad y comunicación | C36: Bienes ligados (vehículos): cada persona registra, corrige y quita sus vehículos (tipo, marca, modelo, año, color y placas) desde Mi cuenta. Quien consulta expedientes los ve en la ficha, sin poder cambiarlos. | D36: Respuesta v3.22 | E36: MVP | F36: Fase 0 | G36: Sprint 5 | H36: H2 · Fase 0 completa | I36: Como persona quiero registrar mis vehículos para que la iglesia los conozca. | J36: Agregar, editar y quitar un vehículo propio; no se puede tocar el de otra persona; queda en la bitácora. | K36: VoBo pendiente | L36: En pruebas | M36: Rama feature/paso-9-oraciones-vehiculos · pruebas de backend y 110 de frontend pasan; lint, estilos y compilación limpios | N36: 2026-10-30 · Vehículos propios en Mi cuenta y consulta en la ficha.
A37: M2A-01 | B37: M2A Cursos de Vida | C37: Catálogo dinámico de cursos; se pueden crear nuevos sin intervención técnica. Incluye «Resolución de Varones» y «Toma de Buenas Decisiones», omitidos en v2. | D37: Recuperado v1 | E37: Fuera del MVP | F37: Fase 3 | G37: — | H37: Posterior | I37: Se define al iniciar la fase. | J37: Se define al iniciar la fase. | K37: VoBo pendiente | L37: Pendiente
A38: M2A-02 | B38: M2A Cursos de Vida | C38: Flexibilidad operativa: sin día ni horario fijo; el día y el ponente pueden cambiar entre ediciones. | D38: v1 / v2 | E38: Fuera del MVP | F38: Fase 3 | G38: — | H38: Posterior | I38: Se define al iniciar la fase. | J38: Se define al iniciar la fase. | K38: VoBo pendiente | L38: Pendiente
A39: M2A-03 | B39: M2A Cursos de Vida | C39: Reposición de clases: el inscrito puede reponer en otro grupo o con otro ponente, a decisión de quien imparte. | D39: v1 / v2 | E39: Fuera del MVP | F39: Fase 3 | G39: — | H39: Posterior | I39: Se define al iniciar la fase. | J39: Se define al iniciar la fase. | K39: VoBo pendiente | L39: Pendiente
A40: M2A-04 | B40: M2A Cursos de Vida | C40: Registro de asistencia por sesión. | D40: v1 / v2 | E40: Fuera del MVP | F40: Fase 3 | G40: — | H40: Posterior | I40: Se define al iniciar la fase. | J40: Se define al iniciar la fase. | K40: VoBo pendiente | L40: Pendiente
A41: M2A-05 | B41: M2A Cursos de Vida | C41: Seguimiento de tareas o actividades opcionales (no sumativas). | D41: v1 / v2 | E41: Fuera del MVP | F41: Fase 3 | G41: — | H41: Posterior | I41: Se define al iniciar la fase. | J41: Se define al iniciar la fase. | K41: VoBo pendiente | L41: Pendiente
A42: M2A-06 | B42: M2A Cursos de Vida | C42: Inscripción: quién se inscribe, cuándo lo hizo, si tiene adeudo y qué incluye el costo (materiales, hospedaje, etc.). | D42: v1 / v2 | E42: Fuera del MVP | F42: Fase 3 | G42: — | H42: Posterior | I42: Se define al iniciar la fase. | J42: Se define al iniciar la fase. | K42: VoBo pendiente | L42: Pendiente
A43: M2A-07 | B43: M2A Cursos de Vida | C43: Registro de pagos, saldo de adeudos y recibo. Por definir: captura manual vs. pasarela de pago, y si se requiere corte de caja. | D43: Nuevo v3 | E43: Fuera del MVP | F43: Fase 3 | G43: — | H43: Posterior | I43: Se define al iniciar la fase. | J43: Se define al iniciar la fase. | K43: Por definir | L43: Pendiente
A44: M2A-08 | B44: M2A Cursos de Vida | C44: Tablero del curso tipo mensajería para avisos antes del curso y días posteriores, con notificación a los inscritos. | D44: Recuperado v1 | E44: Fuera del MVP | F44: Fase 3 | G44: — | H44: Posterior | I44: Se define al iniciar la fase. | J44: Se define al iniciar la fase. | K44: VoBo pendiente | L44: Pendiente
A45: M2A-09 | B45: M2A Cursos de Vida | C45: Evaluación docente configurable: formulario diseñable (tipo Google Forms) aplicado al finalizar el curso. | D45: v1 / v2 | E45: Fuera del MVP | F45: Fase 3 | G45: — | H45: Posterior | I45: Se define al iniciar la fase. | J45: Se define al iniciar la fase. | K45: VoBo pendiente | L45: Pendiente
A46: M2A-10 | B46: M2A Cursos de Vida | C46: Evolución del ponente: historial de evaluaciones por ponente a lo largo del tiempo y entre ediciones. | D46: Recuperado v1 | E46: Fuera del MVP | F46: Fase 3 | G46: — | H46: Posterior | I46: Se define al iniciar la fase. | J46: Se define al iniciar la fase. | K46: VoBo pendiente | L46: Pendiente
A47: M2A-11 | B47: M2A Cursos de Vida | C47: Reconocimiento de participación (diploma) opcional por curso. | D47: v1 / v2 | E47: Fuera del MVP | F47: Fase 3 | G47: — | H47: Posterior | I47: Se define al iniciar la fase. | J47: Se define al iniciar la fase. | K47: VoBo pendiente | L47: Pendiente
A48: M2B-01 | B48: M2B Cursos escolarizados | C48: Control riguroso de asistencia. | D48: v1 / v2 | E48: Fuera del MVP | F48: Fase 3 | G48: — | H48: Posterior | I48: Se define al iniciar la fase. | J48: Se define al iniciar la fase. | K48: VoBo pendiente | L48: Pendiente
... A53: M2B-06 | B53: M2B Cursos escolarizados | C53: Historial académico permanente en el Expediente Digital, aunque cambie el maestro o el alumno pierda su comprobante. | D53: v2 | E53: Fuera del MVP | F53: Fase 3 | G53: — | H53: Posterior | I53: Se define al iniciar la fase. | J53: Se define al iniciar la fase. | K53: VoBo pendiente | L53: Pendiente
A54: M3-01 | B54: M3 Grupos de Conexión | C54: Estructura del grupo con roles: Supervisor (supervisa uno o varios grupos y reporta al Pastor), Líder, Secretario, Anfitrión y Tesorero. | D54: v3 + Obs. 4 | E54: MVP | F54: Fase 1 | G54: Sprint 3 | H54: H3 · MVP (Grupos) | I54: Como supervisor quiero asignar Líder, Secretario, Anfitrión y Tesorero a cada grupo. | J54: Un grupo tiene sus roles asignados; un supervisor ve varios grupos. | K54: VoBo pendiente | L54: En pruebas | M54: Rama feature/grupos-paso-3 · pruebas de backend y 81 de frontend pasan; lint, estilos y compilación limpios | N54: 2026-10-27 · Supervisor, Líder, Secretario, Anfitrión, Tesorero y Asistente por grupo; ahora con cambio de rol, sector (letra), casa (número) y suspensión con motivo.
A55: M3-02 | B55: M3 Grupos de Conexión | C55: Estudio semanal dentro de la app: un registro por semana con PDF para adultos, PDF para niños y audio de la lectura (PDF hasta 15 MB; audio hasta 40 MB). Lo publican Pastor o Anciano y los líderes lo abren desde la reunión, sustituyendo el envío por WhatsApp. El audio admite adelantar y retroceder en iPhone. | D55: v1 / v2 + Respuesta | E55: MVP | F55: Fase 1 | G55: Sprint 3 | H55: H3 · MVP (Grupos) | I55: Como líder quiero recibir el estudio semanal en la app en lugar de WhatsApp. | J55: Publicar el material de la semana; el líder lo abre y queda marca de lectura. | K55: VoBo pendiente | L55: En pruebas | M55: Rama feature/m3-grupos · 88 pruebas de backend y 7 de frontend pasan | N55: 2026-10-24 · PDF adultos, PDF niños y audio por semana; audio con Range para iPhone. Pendiente probar en iOS.
A56: M3-03 | B56: M3 Grupos de Conexión | C56: Pase de lista digital por Secretario o Líder. El Secretario captura y corrige el mismo día; el Líder modifica siempre; el Supervisor solo consulta. Funciona sin conexión: la lista se guarda en el teléfono con la hora real de captura y se envía sola al volver la señal, sin pisar cambios más recientes hechos en línea. Una captura sin conexión se acepta hasta 7 días después y se evalúa contra el día en que se hizo; todo queda en bitácora marcado como diferido. | D56: v3 | E56: MVP | F56: Fase 1 | G56: Sprint 3 | H56: H3 · MVP (Grupos) | I56: Como secretario quiero pasar lista aunque no haya señal. | J56: Pasar lista en modo avión; al reconectar se sincroniza sin duplicados. | K56: VoBo pendiente | L56: En pruebas | M56: Rama feature/nf-06-sin-conexion · 117 pruebas de backend y 27 de frontend; probado en Chrome real con service worker | N56: 2026-10-24 · Pase de lista con y sin conexión.
A57: M3-04 | B57: M3 Grupos de Conexión | C57: Ofrendas regulares y especiales (con concepto) por reunión, cuantificables. El Secretario captura el monto; si el grupo no tiene Secretario, lo suple el Líder. El Tesorero cuenta, escribe su cifra y avala volviendo a escribir su PIN; si el grupo no tiene Tesorero, avalan el Líder o el Pastor, nunca quien capturó. Si la cifra coincide queda «Avalada»; si no, se registra la diferencia y queda «Con diferencia», con aviso visible en el grupo, la reunión y la pantalla del Tesorero para quien pueda consultar. Una ofrenda ya capturada solo se corrige con motivo y vuelve a pendiente para un nuevo aval. El Pastor consulta todo, el Líder y el Supervisor consultan y el Anciano no ve finanzas. Toda suplencia, captura, aval y corrección queda en bitácora. | D57: v3 + Obs. 4 | E57: MVP | F57: Fase 1 | G57: Sprint 4 | H57: H3 · MVP (Grupos) | I57: Como tesorero quiero contar y avalar la ofrenda del grupo. | J57: Capturar monto; el Tesorero captura su cifra y confirma con su PIN; si difiere se registra la diferencia; con aval no se edita sin motivo. | K57: VoBo pendiente | L57: En pruebas | M57: Rama feature/m3-ofrendas-ajustes · 121 pruebas de backend y 14 de frontend pasan | N57: 2026-10-24 · Con suplencias del Líder, diferencias visibles y límites configurables. Falta validar con la iglesia.
A58: M3-05 | B58: M3 Grupos de Conexión | C58: Peticiones de oración con formulario configurable (campos que se agregan, desactivan y reordenan sin programar; cada cambio crea una versión y los campos no se borran). Por defecto: petición, quién la pide y categoría. Las registran el Líder y el Secretario, desde la reunión o desde el grupo; el Pastor también. | D58: v3 | E58: MVP | F58: Fase 1 | G58: Sprint 4 | H58: H3 · MVP (Grupos) | I58: Como líder quiero recoger peticiones de oración con un formulario configurable. | J58: Capturar una petición; el formulario se edita sin código. | K58: VoBo pendiente | L58: En pruebas | M58: Rama feature/m3-peticiones-oracion · 166 pruebas de backend y 32 de frontend pasan; probado contra la base real | N58: 2026-10-24 · Formulario configurable y versionado; captura desde la reunión y el grupo.
A59: M3-06 | B59: M3 Grupos de Conexión | C59: Alcance de lectura de cada petición, elegido por quien la registra con autorización de quien la pide: «Solo líderes» (Líder, Supervisor, Pastor y Anciano), «Mi grupo» (todos los integrantes del grupo y los anteriores) o «Equipo de oración» (además, quien tenga el rol Equipo de oración). El alcance por defecto es configurable. Quien registra siempre ve lo que registró; el Administrador Técnico nunca ve el contenido. Solo líderes y superiores marcan una petición como atendida. Se guardan cifradas y se borran automáticamente a los 30 días, configurable. Consultarlas y atenderlas queda en bitácora sin incluir el texto. | D59: Resp. P8 + Respuesta | E59: MVP | F59: Fase 1 | G59: Sprint 4 | H59: H3 · MVP (Grupos) | I59: Como pastor quiero que las peticiones solo las vea el Líder y superiores y se borren al vencer. | J59: El Secretario no las ve; tras el plazo configurable (por defecto 30 días) se eliminan. | K59: VoBo pendiente | L59: En pruebas | M59: Rama feature/m3-peticiones-oracion · 166 pruebas de backend y 32 de frontend pasan; probado contra la base real | N59: 2026-10-24 · Alcance por petición (líderes, grupo, equipo), cifrado y borrado a los 30 días configurable. Cambia la matriz aprobada: actualizar con la iglesia.
A60: M3-07 | B60: M3 Grupos de Conexión | C60: Dashboard de supervisión («Resumen de grupos») para Supervisor, Líder, Pastor y Anciano sobre los grupos que cada uno puede consultar: asistencia por semana y por grupo, grupos sin lista esta semana, asistencia por debajo de un mínimo configurable (60 % por defecto), ofrendas avaladas, pendientes y con diferencia (solo si el rol ve finanzas) y peticiones activas (solo las que puede leer). No muestra datos de personas. El Secretario y el Tesorero no lo ven. | D60: v3 | E60: MVP básico | F60: Fase 1 | G60: Sprint 5 | H60: H3 · MVP (Grupos) | I60: Como supervisor quiero ver la salud de mis grupos. | J60: El dashboard muestra asistencia, ofrendas y crecimiento según permisos. | K60: VoBo pendiente | L60: En pruebas | M60: Rama feature/m3-dashboard-tablero · 195 pruebas de backend y 39 de frontend pasan; probado contra la base real | N60: 2026-10-25 · Dashboard con asistencia, avisos y datos según rol; umbral configurable.
A61: M3-08 | B61: M3 Grupos de Conexión | C61: Ubicación de zona del grupo para que personas cercanas lo encuentren, sin exponer el domicilio exacto. Por definir. | D61: v3 | E61: Fuera del MVP | F61: Fase 4 | G61: — | H61: Posterior | I61: Se define al iniciar la fase. | J61: Se define al iniciar la fase. | K61: Por definir | L61: Pendiente
A62: M3-09 | B62: M3 Grupos de Conexión | C62: A un grupo asisten miembros de la iglesia (vecinos o no) e invitados del grupo que no asisten a la iglesia. Los invitados se registran como Contacto con datos mínimos y se les puede invitar a consolidación. | D62: Corrección v3.2 | E62: MVP | F62: Fase 1 | G62: Sprint 3 | H62: H3 · MVP (Grupos) | I62: Como secretario quiero registrar invitados del grupo con datos mínimos. | J62: Registrar un invitado como Contacto y marcarlo presente. | K62: VoBo pendiente | L62: En pruebas | M62: Rama feature/paso-5-invitaciones · pruebas de backend y 93 de frontend pasan; lint, estilos y compilación limpios | N62: 2026-10-27 · Los invitados entran al grupo como Contacto cuando el líder aprueba su solicitud por enlace o QR.
A63: M3-10 | B63: M3 Grupos de Conexión | C63: Confidencialidad de ofrendas y asistencias: consulta limitada por rol (matriz por definir) y modificación restringida, todo en bitácora. | D63: Obs. 5 | E63: MVP | F63: Fase 1 | G63: Sprint 4 | H63: H3 · MVP (Grupos) | I63: Como pastor quiero que ofrendas y asistencias sean confidenciales. | J63: La matriz de la sección 3.3 del v3.2 se cumple en pruebas por cada rol. | K63: Por definir | L63: Pendiente
A64: M3-11 | B64: M3 Grupos de Conexión | C64: Tablero de mensajes del grupo: lo publican Líder, Supervisor, Secretario y Pastor; lo leen todos los integrantes activos. Mensajes de hasta 1,000 caracteres, con opción de fijarlos, borrado lógico, contador de mensajes nuevos y conservación configurable (90 días). Pantalla «Avisos» para quien no abre la página del grupo. | D64: Obs. 7 | E64: MVP | F64: Fase 1 | G64: Sprint 5 | H64: H3 · MVP (Grupos) | I64: Como líder quiero un tablero de mensajes de mi grupo. | J64: Publicar y leer mensajes del grupo. | K64: VoBo pendiente | L64: En pruebas | M64: Rama feature/m3-dashboard-tablero · 195 pruebas de backend y 39 de frontend pasan; probado contra la base real | N64: 2026-10-25 · Tablero con fijados, no leídos y retención configurable; la notificación push de mensajes nuevos se entrega con M1-09.
A65: M3-12 | B65: M3 Grupos de Conexión | C65: Reuniones: cada grupo se reúne una vez por semana en casa del líder (día y hora por grupo) y existe una reunión general de líderes, modelada como un grupo de tipo «Líderes». | D65: Respuesta | E65: MVP | F65: Fase 1 | G65: Sprint 3 | H65: H3 · MVP (Grupos) | I65: Se define al iniciar la fase. | J65: Se define al iniciar la fase. | K65: VoBo pendiente | L65: En pruebas | M65: Rama feature/grupos-paso-3 · pruebas de backend y 81 de frontend pasan; lint, estilos y compilación limpios | N65: 2026-10-27 · Una reunión semanal por grupo y grupo tipo Líderes; filtros por día, sector, líder y estado; cada reunión muestra su asistencia, observaciones, peticiones y ofrendas.
A66: M3-13 | B66: M3 Grupos de Conexión | C66: Parámetros configurables sin programar, con pantalla de Configuración y cada cambio en bitácora: monto máximo por ofrenda (1,000,000 por defecto) y si se permite una sola ofrenda regular por reunión. Solo Pastor y Administrador Técnico. | D66: Respuesta | E66: MVP | F66: Fase 1 | G66: Sprint 4 | H66: H3 · MVP (Grupos) | I66: Se define al iniciar la fase. | J66: Se define al iniciar la fase. | K66: VoBo pendiente | L66: En pruebas | M66: Rama feature/m3-ofrendas-ajustes · 121 pruebas de backend y 14 de frontend pasan | N66: 2026-10-24 · Pantalla Configuración: monto máximo y una regular por reunión.
A67: M3-14 | B67: M3 Grupos de Conexión | C67: Componente de peticiones reutilizable: cualquier módulo (grupos hoy; cursos o eventos después) se registra como origen y decide quién registra y qué nivel de acceso tiene cada persona. Toda petición guarda su origen de forma inmutable (tipo, identificador y una etiqueta fija, por ejemplo «Grupo de Conexión · Norte · reunión del 22/10/2026») y lo muestra siempre en el listado. | D67: Respuesta | E67: MVP | F67: Fase 1 | G67: Sprint 4 | H67: H3 · MVP (Grupos) | I67: Se define al iniciar la fase. | J67: Se define al iniciar la fase. | K67: VoBo pendiente | L67: En pruebas | M67: Rama feature/m3-peticiones-oracion · 166 pruebas de backend y 32 de frontend pasan; probado contra la base real | N67: 2026-10-24 · Origen inmutable y visible; probado con un segundo origen de prueba para verificar la reutilización.
A68: M3-15 | B68: M3 Grupos de Conexión | C68: Equipo de oración: rol configurable (Equipo de oración) que se asigna a las personas que se reúnen a orar por las peticiones compartidas con ese alcance; no da acceso a nada más. Opción de ocultar el nombre de quien pide: los campos del formulario marcados «identifica a la persona» solo los ven líderes y quien registró. Al capturar se muestra una leyenda que pide confirmar la autorización de quien pide, indica quién la leerá y cuándo se borra. | D68: Respuesta | E68: MVP | F68: Fase 1 | G68: Sprint 4 | H68: H3 · MVP (Grupos) | I68: Se define al iniciar la fase. | J68: Se define al iniciar la fase. | K68: VoBo pendiente | L68: En pruebas | M68: Rama feature/m3-peticiones-oracion · 166 pruebas de backend y 32 de frontend pasan; probado contra la base real | N68: 2026-10-24 · Rol Equipo de oración, nombre oculto y leyenda de privacidad al capturar. Falta el aviso de privacidad oficial de la iglesia.
A69: M4-01 | B69: M4 Kids Check-In/Out | C69: Sustitución de la ficha física de papel. | D69: v1 / v2 | E69: Fuera del MVP | F69: Fase 2 | G69: — | H69: Posterior | I69: Se define al iniciar la fase. | J69: Se define al iniciar la fase. | K69: VoBo pendiente | L69: Pendiente
A70: M4-02 | B70: M4 Kids Check-In/Out | C70: Registro de ingreso del menor con salón o clase asignada y generación de código único. | D70: v1 + Nuevo v3 | E70: Fuera del MVP | F70: Fase 2 | G70: — | H70: Posterior | I70: Se define al iniciar la fase. | J70: Se define al iniciar la fase. | K70: VoBo pendiente | L70: Pendiente
A71: M4-03 | B71: M4 Kids Check-In/Out | C71: Código QR dinámico o OTP temporal en la PWA del padre o tutor. | D71: v2 | E71: Fuera del MVP | F71: Fase 2 | G71: — | H71: Posterior | I71: Se define al iniciar la fase. | J71: Se define al iniciar la fase. | K71: VoBo pendiente | L71: Pendiente
A72: M4-04 | B72: M4 Kids Check-In/Out | C72: Validación al entregar: el servidor de Kids escanea el código y confirma identidad y fotografía del tutor autorizado en el Expediente Digital. | D72: v2 | E72: Fuera del MVP | F72: Fase 2 | G72: — | H72: Posterior | I72: Se define al iniciar la fase. | J72: Se define al iniciar la fase. | K72: VoBo pendiente | L72: Pendiente
A73: M4-05 | B73: M4 Kids Check-In/Out | C73: Alternativa para tutores sin smartphone, sin batería o sin conexión (p. ej. código por SMS o comprobante imprimible con identificación). Por definir. | D73: Nuevo v3 | E73: Fuera del MVP | F73: Fase 2 | G73: — | H73: Posterior | I73: Se define al iniciar la fase. | J73: Se define al iniciar la fase. | K73: Por definir | L73: Pendiente
A74: M4-06 | B74: M4 Kids Check-In/Out | C74: Autorización temporal de un tercero para recoger al menor, con aprobación del tutor registrado. | D74: Nuevo v3 | E74: Fuera del MVP | F74: Fase 2 | G74: — | H74: Posterior | I74: Se define al iniciar la fase. | J74: Se define al iniciar la fase. | K74: VoBo pendiente | L74: Pendiente
A75: M4-07 | B75: M4 Kids Check-In/Out | C75: Caducidad del código y bitácora de cada entrega (quién recogió, quién entregó, hora). | D75: Nuevo v3 | E75: Fuera del MVP | F75: Fase 2 | G75: — | H75: Posterior | I75: Se define al iniciar la fase. | J75: Se define al iniciar la fase. | K75: VoBo pendiente | L75: Pendiente
A76: M4-08 | B76: M4 Kids Check-In/Out | C76: Funcionamiento sin conexión o con conexión degradada para el check-out. | D76: Nuevo v3 | E76: Fuera del MVP | F76: Fase 2 | G76: — | H76: Posterior | I76: Se define al iniciar la fase. | J76: Se define al iniciar la fase. | K76: VoBo pendiente | L76: Pendiente
A77: M5-01 | B77: M5 Áreas y servidores | C77: Catálogo mínimo de áreas y asignación de servidores. Versión reducida del módulo 5, necesaria para permisos por área. Sirve como primer censo. | D77: v3 | E77: MVP mínimo | F77: Fase 0 | G77: Sprint 1 | H77: H2 · Fase 0 completa | I77: Como pastor quiero un catálogo de áreas con su personal para conocer la estructura. | J77: Crear un área, asignar servidores y ver el conteo real. | K77: VoBo pendiente | L77: Pendiente
A78: M5-02 | B78: M5 Áreas y servidores | C78: Roles jerárquicos dentro de cada área (directores, líderes, maestros, servidores). | D78: v1 | E78: Fuera del MVP | F78: Fase 4 | G78: — | H78: Posterior | I78: Se define al iniciar la fase. | J78: Se define al iniciar la fase. | K78: VoBo pendiente | L78: Pendiente
A79: M5-03 | B79: M5 Áreas y servidores | C79: Organigrama y número real de servidores activos, directores y líderes por área. | D79: v2 | E79: Fuera del MVP | F79: Fase 4 | G79: — | H79: Posterior | I79: Se define al iniciar la fase. | J79: Se define al iniciar la fase. | K79: VoBo pendiente | L79: Pendiente
A80: M5-04 | B80: M5 Áreas y servidores | C80: Control de asistencia a turnos o servicios. | D80: v1 / v2 | E80: Fuera del MVP | F80: Fase 4 | G80: — | H80: Posterior | I80: Se define al iniciar la fase. | J80: Se define al iniciar la fase. | K80: VoBo pendiente | L80: Pendiente
... A96: NF-01 | B96: No funcionales | C96: Cumplimiento de la LFPDPPP: aviso de privacidad, consentimiento y derechos ARCO. | D96: v3 | E96: MVP | F96: Fase 0 | G96: Sprint 1 | H96: H1 · 18-oct (núcleo Fase 0) | I96: Como iglesia queremos cumplir con la LFPDPPP. | J96: Aviso de privacidad, consentimiento y atención de derechos ARCO disponibles. | K96: VoBo pendiente | L96: Pendiente
A97: NF-02 | B97: No funcionales | C97: Cifrado en tránsito y en reposo. Cifrado adicional a nivel de campo para peticiones de oración. | D97: v3 | E97: MVP | F97: Fase 0 | G97: Sprint 0 | H97: H1 · 18-oct (núcleo Fase 0) | I97: Como iglesia queremos proteger los datos sensibles. | J97: HTTPS obligatorio y peticiones de oración ilegibles directamente en la base. | K97: VoBo pendiente | L97: En pruebas | M97: Rama feature/m3-peticiones-oracion · 166 pruebas de backend y 32 de frontend pasan; probado contra la base real | N97: 2026-10-24 · Peticiones cifradas a nivel de campo; falta cifrado en reposo de toda la base (proveedor de nube).
A98: NF-03 | B98: No funcionales | C98: Bitácora de auditoría de solo-añadir: quién consultó o modificó expedientes, ofrendas y asistencias. | D98: v3 | E98: MVP | F98: Fase 0 | G98: Sprint 1 | H98: H1 · 18-oct (núcleo Fase 0) | I98: Como pastor quiero una bitácora que nadie pueda alterar. | J98: El usuario de la aplicación no puede actualizar ni borrar registros de bitácora. | K98: VoBo pendiente | L98: En pruebas | M98: Rama feature/nf-03-bitacora · 69 pruebas de backend pasan | N98: 2026-10-10 · Bloqueo en aplicación y trigger de PostgreSQL (UPDATE/DELETE/TRUNCATE); pantalla de consulta con permiso bitacora.ver.
A99: NF-04 | B99: No funcionales | C99: Respaldos automáticos diarios cifrados y prueba periódica de restauración. | D99: v3 | E99: MVP | F99: Fase 0 | G99: Sprint 0 | H99: H1 · 18-oct (núcleo Fase 0) | I99: Como iglesia queremos no perder información. | J99: Respaldo diario cifrado y restauración probada en un ambiente de pruebas. | K99: VoBo pendiente | L99: Pendiente
A100: NF-05 | B100: No funcionales | C100: Disponibilidad esperada en horarios de servicio (fines de semana y reuniones de grupo). Por definir meta. | D100: Nuevo v3 | E100: Fuera del MVP | F100: Transversal | G100: — | H100: Posterior | I100: Se define al iniciar la fase. | J100: Se define al iniciar la fase. | K100: Por definir | L100: Pendiente
A101: NF-06 | B101: No funcionales | C101: Pase de lista sin conexión con sincronización posterior (reuniones en domicilios con mala señal). | D101: v3 | E101: MVP | F101: Fase 0 | G101: Sprint 3 | H101: H3 · MVP (Grupos) | I101: Como secretario quiero que el pase de lista funcione sin señal. | J101: Prueba en modo avión y sincronización al reconectar. | K101: VoBo pendiente | L101: En pruebas | M101: Rama feature/nf-06-sin-conexion · 117 pruebas de backend y 27 de frontend; probado en Chrome real con service worker | N101: 2026-10-24 · Probado de punta a punta en Chrome (sin red → cola → sincronización). Pendiente probar en Android e iOS reales.
A102: NF-07 | B102: No funcionales | C102: Funciona en Android, iOS y escritorio. En iOS, las notificaciones push requieren instalar la PWA; el respaldo por WhatsApp cubre el resto. | D102: v3 | E102: MVP | F102: Fase 0 | G102: Sprint 0 | H102: H1 · 18-oct (núcleo Fase 0) | I102: Como usuario quiero usar el sistema en mi dispositivo. | J102: Pruebas en Android, iOS y escritorio; push en iOS con la PWA instalada y respaldo por WhatsApp. | K102: VoBo pendiente | L102: Pendiente
A103: NF-08 | B103: No funcionales | C103: Dimensionamiento para ~1,000 personas, con picos los fines de semana, y margen de crecimiento. | D103: Resp. P8 | E103: MVP | F103: Fase 0 | G103: Sprint 0 | H103: H1 · 18-oct (núcleo Fase 0) | I103: Como iglesia queremos que el sistema soporte a ~1,000 personas. | J103: Prueba de carga con volumen representativo (por definir) sin degradación. | K103: VoBo pendiente | L103: Pendiente
A104: NF-09 | B104: No funcionales | C104: Reportes transversales: asistencia, finanzas, crecimiento de la iglesia, exportables a Excel y PDF. | D104: Nuevo v3 | E104: Fuera del MVP | F104: Transversal | G104: — | H104: Posterior | I104: Se define al iniciar la fase. | J104: Se define al iniciar la fase. | K104: VoBo pendiente | L104: Pendiente
A105: NF-10 | B105: No funcionales | C105: Usabilidad para personas mayores: tipografía grande, alto contraste, flujos cortos (ver sección 5). | D105: v3 + Obs. 1 | E105: MVP | F105: Fase 0 | G105: Sprint 0 | H105: H1 · 18-oct (núcleo Fase 0) | I105: Como persona mayor quiero una interfaz fácil de leer y usar. | J105: Texto base 18 px, botones de al menos 48 px, contraste AA; prueba con usuarios mayores. | K105: VoBo pendiente | L105: Pendiente

Sheet Observaciones
A1: Obs. | B1: Resumen de la observación | C1: Requerimientos | D1: Resolución | E1: Estado
A2: 1 | B2: ¿PWA o nativa? Considerar permisos, costos y usuarios mayores. | C2: NF-07, NF-10 | D2: PWA primero; lógica separada para envolver como app nativa si se justifica. | E2: Decidido
A3: 2 | B3: Diseñador dinámico con relaciones para reportes y estadísticas. | C3: CFG-06, CFG-07, CFG-08 | D3: Modelo híbrido: tablas fijas + campos personalizados + campos de relación. | E3: En MVP (Sprint 2)
A4: 3 | B4: Distinguir si el inscrito es de la iglesia local; pedir WhatsApp. | C4: M1-12, M1-13 | D4: Tres niveles de registro y atributo de procedencia. Su uso en cursos llega en Fase 3. | E4: En MVP (Sprint 1)
A5: 4 | B5: Tesorero con firma que avala la cifra. | C5: M3-01, M3-04 | D5: Rol Tesorero y aval electrónico simple con diferencia registrada. | E5: En MVP (Sprint 4)
A6: 5 | B6: Confidencialidad de ofrendas y asistencias, con bitácora. | C6: M1-16, M3-10 | D6: Matriz de confidencialidad aprobada (v3.2, sección 3.3). | E6: En MVP (Sprint 1 y 4)
A7: 6 | B7: Alternativa a M4-05: check-out sin teléfono. | C7: M4-05 | D7: Validación por el servidor del salón con fotos y bitácora. | E7: Fase 2
A8: 7 | B8: Dashboard y tablero de mensajes por módulo (se omiten los «roles de servir»). | C8: M1-19, M3-11 | D8: Componente genérico reutilizable. | E8: En MVP (Sprint 5)
A9: 8 | B9: Datos de salud en el EDU y medicamentos con caducidad. | C9: M6-07 y ficha de salud | D9: Fuera del MVP; el modelo del EDU se prepara para admitirlos. | E9: Posterior
A10: 9 | B10: Registro breve y seguimiento de personas nuevas. | C10: M1-12, M1-18, M3-09 | D10: Contacto con WhatsApp, responsable y estados. | E10: En MVP (Sprint 1 y 2)
A11: 10 | B11: Reserva de lugares y sobrecupo autorizado en eventos. | C11: M7-04 | D11: Reserva por cantidad y sobrecupo con autorización y bitácora. | E11: Fase 4
A12: P8-1 | B12: Respuestas: Ancianos como Pastor, con limitantes en finanzas. | C12: M1-07 | D12: Incorporado en RBAC y en la matriz de confidencialidad. | E12: En MVP (Sprint 1)
... A31: P1-12 | B31: Pruebas 1: el rol de Super Usuario es el único que asigna Administrador técnico. | C31: M1-07 | D31: Confirmado por Edgar el 27-oct-2026; el sistema ya lo cumple (nadie otorga un rol más alto que el suyo) y hay prueba. | E31: Hecho (v3.15)

Sheet Origen v1
A1: Necesidad del levantamiento original (v1) | B1: Requerimientos actuales | C1: Situación | D1: Alcance
A2: Roles con permisos distintos por módulo (Pastor, ancianos, líderes, servidores) | B2: M1-07, M1-08 | C2: Cubierto | D2: MVP
A3: Cursos de vida: listas de asistencia | B3: M2A-04 | C3: Cubierto | D3: Fase 3
A4: Cursos de vida: control de tareas o actividades (no requerido) | B4: M2A-05 | C4: Cubierto | D4: Fase 3
A5: Cursos de vida: evolución del ponente | B5: M2A-10 | C5: Recuperado en v3 | D5: Fase 3
A6: Cursos de vida: anuncios y tablero tipo WhatsApp antes y después del curso | B6: M2A-08 | C6: Recuperado en v3 | D6: Fase 3
A7: Cursos de vida: inscripción, adeudo y qué incluye el costo | B7: M2A-06, M2A-07 | C7: Cubierto | D7: Fase 3
A8: Cursos de vida: cambio de día, ponente y reposición de clases | B8: M2A-02, M2A-03 | C8: Cubierto | D8: Fase 3
A9: Cursos de vida: evaluación de ponentes diseñable (tipo Google Forms) | B9: M2A-09, CFG-01 | C9: Cubierto | D9: Fase 3
A10: Cursos de vida: reconocimiento opcional | B10: M2A-11 | C10: Cubierto | D10: Fase 3
A11: Cursos «Resolución de varones» y «Toma de buenas decisiones» | B11: M2A-01 | C11: Recuperado en v3 | D11: Fase 3
A12: Cursos escolarizados: asistencia, tareas, calificación, exámenes y boleta con formato | B12: M2B-01 a M2B-06 | C12: Cubierto | D12: Fase 3
... A27: Grupos de conexión: el supervisor reporta al Pastor | B27: M3-01, M3-07 | C27: Cubierto | D27: MVP
